[
  {
    "name": "Hornsea Freeport",
    "lat": 53.898356,
    "lon": -0.170969,
    "sequence": 1
  },
  {
    "name": "Hornsea Rolston Road",
    "lat": 53.899907,
    "lon": -0.167735,
    "sequence": 2
  },
  {
    "name": "Hornsea Rolston Road",
    "lat": 53.901491,
    "lon": -0.169066,
    "sequence": 3
  },
  {
    "name": "Hornsea Rolston Road",
    "lat": 53.903808,
    "lon": -0.170654,
    "sequence": 4
  },
  {
    "name": "Hornsea Southgate",
    "lat": 53.904913,
    "lon": -0.1712,
    "sequence": 5
  },
  {
    "name": "Hornsea Southgate",
    "lat": 53.908621,
    "lon": -0.172073,
    "sequence": 6
  },
  {
    "name": "Hornsea Newbegin",
    "lat": 53.910806,
    "lon": -0.172708,
    "sequence": 7
  },
  {
    "name": "Hornsea New Road",
    "lat": 53.912401,
    "lon": -0.166472,
    "sequence": 8
  },
  {
    "name": "Hornsea Marine Drive",
    "lat": 53.915508,
    "lon": -0.161585,
    "sequence": 9
  },
  {
    "name": "Eastgate Surgery",
    "lat": 53.914676,
    "lon": -0.168885,
    "sequence": 10
  },
  {
    "name": "Hornsea Cliff Road",
    "lat": 53.920439,
    "lon": -0.167749,
    "sequence": 11
  },
  {
    "name": "Hornsea (Caravan Park)",
    "lat": 53.923771,
    "lon": -0.16937,
    "sequence": 12
  }
]